panel_material_ui/NotificationArea.jsx
panel_material_ui/__init__.py
panel_material_ui/__version.py
panel_material_ui/_param.py
panel_material_ui/_utils.py
panel_material_ui/_version.py
panel_material_ui/base.py
panel_material_ui/description.jsx
panel_material_ui/menu.jsx
panel_material_ui/notifications.py
panel_material_ui/param.py
panel_material_ui/theme.py
panel_material_ui/utils.js
panel_material_ui/_templates/base.html
panel_material_ui/chat/ChatArea.jsx
panel_material_ui/chat/ChatMessage.jsx
panel_material_ui/chat/ChatStep.jsx
panel_material_ui/chat/__init__.py
panel_material_ui/chat/feed.py
panel_material_ui/chat/input.py
panel_material_ui/chat/interface.py
panel_material_ui/chat/message.py
panel_material_ui/chat/step.py
panel_material_ui/dist/emotion-cache-shim.js
panel_material_ui/dist/emotion-react-shim.js
panel_material_ui/dist/material-icons-JLIDJUWE.woff
panel_material_ui/dist/material-icons-LEZCGFVT.woff2
panel_material_ui/dist/material-icons-outlined-7BWLPMFK.woff2
panel_material_ui/dist/material-icons-outlined-PCUTWIDZ.woff
panel_material_ui/dist/material-ui-shim.js
panel_material_ui/dist/material-ui-styles-shim.js
panel_material_ui/dist/panel-material-ui.bundle.css
panel_material_ui/dist/panel-material-ui.bundle.js
panel_material_ui/dist/react-dom-client-shim.js
panel_material_ui/dist/react-dom-shim.js
panel_material_ui/dist/react-is-shim.js
panel_material_ui/dist/react-jsx-runtime-shim.js
panel_material_ui/dist/react-shim.js
panel_material_ui/dist/roboto-cyrillic-400-normal-QMHKB7XT.woff2
panel_material_ui/dist/roboto-cyrillic-400-normal-VGV4HTWX.woff
panel_material_ui/dist/roboto-cyrillic-700-normal-3QDRAX5C.woff
panel_material_ui/dist/roboto-cyrillic-700-normal-LJ3LP5Y5.woff2
panel_material_ui/dist/roboto-cyrillic-ext-400-normal-DEVHEAF7.woff
panel_material_ui/dist/roboto-cyrillic-ext-400-normal-SRSDFWJ5.woff2
panel_material_ui/dist/roboto-cyrillic-ext-700-normal-7Q4EPXM3.woff2
panel_material_ui/dist/roboto-cyrillic-ext-700-normal-UFDZGWZY.woff
panel_material_ui-0.8.1.dist-info/METADATA
panel_material_ui-0.8.1.dist-info/WHEEL
panel_material_ui-0.8.1.dist-info/licenses/LICENSE.txt
panel_material_ui-0.8.1.dist-info/RECORD
